Timage/__init__.py
Timage/change_system.py
Timage/main.py
Timage-0.0.2.dist-info/LICENSE
Timage-0.0.2.dist-info/METADATA
Timage-0.0.2.dist-info/WHEEL
Timage-0.0.2.dist-info/top_level.txt
Timage-0.0.2.dist-info/RECORD
