Metadata-Version: 2.1
Name: Timage
Version: 0.0.2
Summary: Hide text into image
Home-page: https://github.com/HaykSD/Text-into-image
Author: Hayk Sardaryan
Author-email: <hayk4536@gmail.com>
License: UNKNOWN
Keywords: python,steganography,text image,text coder
Platform: UNKNOWN
Classifier: Development Status :: 1 - Planning
Classifier: Intended Audience :: Developers
Classifier: Programming Language :: Python :: 3
Classifier: Operating System :: Unix
Classifier: Operating System :: MacOS :: MacOS X
Classifier: Operating System :: Microsoft :: Windows
Requires-Dist: numpy
Requires-Dist: Pillow
